setup.cfg
setup.py
encryptit/__init__.py
encryptit/__main__.py
encryptit/decoder.py
encryptit/dump_json.py
encryptit/exceptions.py
encryptit/mixins.py
encryptit/openpgp_message.py
encryptit/openpgp_packet.py
encryptit/packet_location.py
encryptit/stream_utils.py
encryptit.egg-info/PKG-INFO
encryptit.egg-info/SOURCES.txt
encryptit.egg-info/dependency_links.txt
encryptit.egg-info/entry_points.txt
encryptit.egg-info/requires.txt
encryptit.egg-info/top_level.txt
encryptit/cli/__init__.py
encryptit/cli/dump_json.py
encryptit/compat/__init__.py
encryptit/compat/abstract_class_method.py
encryptit/compat/struct_unpack.py
encryptit/packets/__init__.py
encryptit/packets/base_packet_body.py
encryptit/packets/factory.py
encryptit/packets/generic_packet_body.py
encryptit/packets/generic_packet_header.py
encryptit/packets/new_format_packet_header.py
encryptit/packets/old_format_packet_header.py
encryptit/packets/packet_type.py
encryptit/tests/__init__.py
encryptit/tests/sample_files.py
encryptit/tests/cli/__init__.py
encryptit/tests/cli/test_cli_main.py
encryptit/tests/cli/test_dump_json.py
encryptit/tests/compat/__init__.py
encryptit/tests/compat/test_struct_unpack.py
encryptit/tests/decoder/__init__.py
encryptit/tests/decoder/test_consume_header.py
encryptit/tests/decoder/test_find_packets.py
encryptit/tests/dump_json/__init__.py
encryptit/tests/dump_json/test_dump_stream.py
encryptit/tests/dump_json/test_encoder.py
encryptit/tests/openpgp_message/__init__.py
encryptit/tests/openpgp_message/test_serialize.py
encryptit/tests/packet_location/__init__.py
encryptit/tests/packet_location/test_packet_location.py
encryptit/tests/packets/__init__.py
encryptit/tests/packets/test_base_packet_body.py
encryptit/tests/test_utils/__init__.py
encryptit/tests/test_utils/assert_is_instance_func.py